<?xml version="1.0" encoding="utf-8" ?>
<dwsync>
<file name="accordion.png" server="brentbook.com" local="129691670620000000" remote="130078827600000000" />
<file name="button.png" server="brentbook.com" local="129691673840000000" remote="130078827600000000" />
<file name="column.png" server="brentbook.com" local="129691672300000000" remote="130078827600000000" />
<file name="divider.png" server="brentbook.com" local="129691681260000000" remote="130078828200000000" />
<file name="dropcap.png" server="brentbook.com" local="129691741300000000" remote="130078828200000000" />
<file name="frame.png" server="brentbook.com" local="129703850240000000" remote="130078828200000000" />
<file name="gdl-gallery.png" server="brentbook.com" local="129744232260000000" remote="130078828200000000" />
<file name="list.png" server="brentbook.com" local="129691678560000000" remote="130078828200000000" />
<file name="message-box.png" server="brentbook.com" local="129701176460000000" remote="130078828200000000" />
<file name="price-item.png" server="brentbook.com" local="129702949540000000" remote="130078828200000000" />
<file name="quote.png" server="brentbook.com" local="129691741160000000" remote="130078828200000000" />
<file name="social.png" server="brentbook.com" local="129691679580000000" remote="130078828200000000" />
<file name="space.png" server="brentbook.com" local="129691665340000000" remote="130078828200000000" />
<file name="tab.png" server="brentbook.com" local="129691671160000000" remote="130078828200000000" />
<file name="testimonial.png" server="brentbook.com" local="129691680360000000" remote="130078828200000000" />
<file name="toggle-box.png" server="brentbook.com" local="129691674940000000" remote="130078828200000000" />
<file name="vimeo.png" server="brentbook.com" local="129691677040000000" remote="130078828200000000" />
<file name="youtube.png" server="brentbook.com" local="129691677420000000" remote="130078828200000000" />
</dwsync>