<?xml version="1.0" encoding="utf-8" ?>
<dwsync>
<file name="anythingslider.css" server="brentbook.com" local="129709384560000000" remote="130078834200000000" />
<file name="flexslider.css" server="brentbook.com" local="129987810760000000" remote="130078834200000000" />
<file name="ie-style.php" server="brentbook.com" local="129875852040000000" remote="130078834800000000" />
<file name="ie7-style.css" server="brentbook.com" local="130056841700000000" remote="130078834800000000" />
<file name="layout-responsive.css" server="brentbook.com" local="130058713160000000" remote="130078834800000000" />
<file name="layout.css" server="brentbook.com" local="130058712660000000" remote="130078834800000000" />
<file name="nivo-slider-style.css" server="brentbook.com" local="129979006400000000" remote="130078834800000000" />
<file name="nivo-slider.css" server="brentbook.com" local="129979024620000000" remote="130078834800000000" />
<file name="prettyPhoto.css" server="brentbook.com" local="129709383880000000" remote="130078834800000000" />
<file name="skeleton-responsive.css" server="brentbook.com" local="130054168240000000" remote="130078834800000000" />
<file name="skeleton.css" server="brentbook.com" local="130058708220000000" remote="130078834800000000" />
<file name="superfish.css" server="brentbook.com" local="130056782880000000" remote="130078834800000000" />
</dwsync>